abstract_ai_test/__init__.py
abstract_ai_test/setup.py
abstract_ai_test/src/__init__.py
abstract_ai_test/src/main.py
abstract_api_test/__init__.py
abstract_api_test/setup.py
abstract_api_test/src/__init__.py
abstract_api_test/src/main.py
abstract_audio_test/__init__.py
abstract_audio_test/setup.py
abstract_audio_test/src/__init__.py
abstract_audio_test/src/main.py
abstract_authority_replica_test/__init__.py
abstract_authority_replica_test/setup.py
abstract_authority_replica_test/src/__init__.py
abstract_authority_replica_test/src/main.py
abstract_authority_test/__init__.py
abstract_authority_test/setup.py
abstract_authority_test/src/__init__.py
abstract_authority_test/src/main.py
abstract_crypto_test/__init__.py
abstract_crypto_test/setup.py
abstract_crypto_test/src/__init__.py
abstract_crypto_test/src/main.py
abstract_gui_test/__init__.py
abstract_gui_test/setup.py
abstract_gui_test/src/__init__.py
abstract_gui_test/src/main.py
abstract_images_test/__init__.py
abstract_images_test/setup.py
abstract_images_test/src/__init__.py
abstract_images_test/src/main.py
abstract_modules_test/__init__.py
abstract_modules_test/setup.py
abstract_modules_test/src/__init__.py
abstract_modules_test/src/main.py
abstract_paths_test/__init__.py
abstract_paths_test/setup.py
abstract_paths_test/src/__init__.py
abstract_paths_test/src/main.py
abstract_security_test/__init__.py
abstract_security_test/setup.py
abstract_security_test/src/__init__.py
abstract_security_test/src/main.py
abstract_threading_test/__init__.py
abstract_threading_test/setup.py
abstract_threading_test/src/__init__.py
abstract_threading_test/src/main.py
abstract_utilities_test/__init__.py
abstract_utilities_test/setup.py
abstract_utilities_test/src/__init__.py
abstract_utilities_test/src/main.py
abstract_web_aggregation_test/__init__.py
abstract_web_aggregation_test/setup.py
abstract_web_aggregation_test/src/__init__.py
abstract_web_aggregation_test/src/main.py
abstract_workstation_test/__init__.py
abstract_package_test-0.0.1.dist-info/LICENSE
abstract_package_test-0.0.1.dist-info/METADATA
abstract_package_test-0.0.1.dist-info/WHEEL
abstract_package_test-0.0.1.dist-info/entry_points.txt
abstract_package_test-0.0.1.dist-info/top_level.txt
abstract_package_test-0.0.1.dist-info/RECORD
