Metadata-Version: 2.1
Name: abstract-package-test
Version: 0.0.1
Summary: abstract_package_test is a Python module within the abstract_package_test package.
Home-page: https://github.com/AbstractEndeavors/abstract_package_test/abstract_package_test
Author: putkoff
Author-email: partners@abstractendeavors.com
Classifier: Development Status :: 3 - Alpha
Classifier: Intended Audience :: Developers
Classifier: License :: OSI Approved :: MIT License
Classifier: Programming Language :: Python :: 3
Classifier: Programming Language :: Python :: 3.11
Classifier: Operating System :: OS Independent
Requires-Python: >=3.6
License-File: LICENSE
